README.md
setup.py
qth_zwave/__init__.py
qth_zwave/version.py
qth_zwave.egg-info/.gitignore
qth_zwave.egg-info/PKG-INFO
qth_zwave.egg-info/SOURCES.txt
qth_zwave.egg-info/dependency_links.txt
qth_zwave.egg-info/entry_points.txt
qth_zwave.egg-info/requires.txt
qth_zwave.egg-info/top_level.txt